gaggle/__init__.py
gaggle/client.py
gaggle-0.2.1.dist-info/WHEEL
gaggle-0.2.1.dist-info/METADATA
gaggle-0.2.1.dist-info/RECORD
